pipeline_viz/__init__.py
pipeline_viz/pipeline_viz.py
pipeline_viz/utils.py
tests/__init__.py
tests/pipeline_test.py
tests/test_pipeline_viz.py
pipeline_viz-0.1.2.dist-info/LICENSE
pipeline_viz-0.1.2.dist-info/METADATA
pipeline_viz-0.1.2.dist-info/WHEEL
pipeline_viz-0.1.2.dist-info/top_level.txt
pipeline_viz-0.1.2.dist-info/RECORD
