Metadata-Version: 2.1
Name: pipeline-viz
Version: 0.1.2
Summary: Visualization tool for sklearn pipelines
Home-page: https://github.com/pritiyadav888/visualize_pipeline.git
Author: Pritii Yadav
Author-email: pritiyadav888@gmail.com
License: UNKNOWN
Platform: UNKNOWN
License-File: LICENSE
Requires-Dist: numpy
Requires-Dist: matplotlib
Requires-Dist: networkx
Requires-Dist: plotly
Requires-Dist: scikit-learn
